{"id":"bk3v","dependencies":[{"name":"E:\\dev\\projects\\department\\mathfiles\\mathfiles-backend\\package.json","includedInParent":true,"mtime":1534490769265},{"name":"./Base","loc":{"line":2,"column":26},"parent":"E:\\dev\\projects\\department\\mathfiles\\mathfiles-backend\\app\\models\\TechnicalReport.js","resolved":"E:\\dev\\projects\\department\\mathfiles\\mathfiles-backend\\app\\models\\Base.js"}],"generated":{"js":"const e=require(\"sequelize\"),T=require(\"./Base\"),r=T.define(\"TechnicalReport\",{Tech_SNO:{type:e.INTEGER,primaryKey:!0},Tech_CODE:e.INTEGER,Tech_DCODE:e.STRING,Tech_Title:e.STRING,Tech_Authors:e.STRING,Tech_Year:e.INTEGER},{tableName:\"Tech_reports\",updatedAt:!1,createdAt:!1});module.exports=r;","map":{"mappings":[{"source":"app\\models\\TechnicalReport.js","original":{"line":1,"column":0},"generated":{"line":1,"column":0}},{"source":"app\\models\\TechnicalReport.js","name":"Sequelize","original":{"line":1,"column":6},"generated":{"line":1,"column":6}},{"source":"app\\models\\TechnicalReport.js","name":"require","original":{"line":1,"column":18},"generated":{"line":1,"column":8}},{"source":"app\\models\\TechnicalReport.js","original":{"line":1,"column":26},"generated":{"line":1,"column":16}},{"source":"app\\models\\TechnicalReport.js","name":"sequelize","original":{"line":2,"column":6},"generated":{"line":1,"column":29}},{"source":"app\\models\\TechnicalReport.js","name":"require","original":{"line":2,"column":18},"generated":{"line":1,"column":31}},{"source":"app\\models\\TechnicalReport.js","original":{"line":2,"column":26},"generated":{"line":1,"column":39}},{"source":"app\\models\\TechnicalReport.js","name":"TechnicalReport","original":{"line":3,"column":6},"generated":{"line":1,"column":49}},{"source":"app\\models\\TechnicalReport.js","name":"sequelize","original":{"line":3,"column":24},"generated":{"line":1,"column":51}},{"source":"app\\models\\TechnicalReport.js","name":"define","original":{"line":3,"column":34},"generated":{"line":1,"column":53}},{"source":"app\\models\\TechnicalReport.js","original":{"line":4,"column":2},"generated":{"line":1,"column":60}},{"source":"app\\models\\TechnicalReport.js","original":{"line":5,"column":2},"generated":{"line":1,"column":78}},{"source":"app\\models\\TechnicalReport.js","original":{"line":6,"column":14},"generated":{"line":1,"column":79}},{"source":"app\\models\\TechnicalReport.js","original":{"line":6,"column":14},"generated":{"line":1,"column":88}},{"source":"app\\models\\TechnicalReport.js","name":"Sequelize","original":{"line":7,"column":12},"generated":{"line":1,"column":89}},{"source":"app\\models\\TechnicalReport.js","name":"Sequelize","original":{"line":7,"column":12},"generated":{"line":1,"column":94}},{"source":"app\\models\\TechnicalReport.js","name":"INTEGER","original":{"line":7,"column":22},"generated":{"line":1,"column":96}},{"source":"app\\models\\TechnicalReport.js","original":{"line":8,"column":18},"generated":{"line":1,"column":104}},{"source":"app\\models\\TechnicalReport.js","original":{"line":8,"column":18},"generated":{"line":1,"column":116}},{"source":"app\\models\\TechnicalReport.js","name":"Sequelize","original":{"line":10,"column":15},"generated":{"line":1,"column":119}},{"source":"app\\models\\TechnicalReport.js","name":"Sequelize","original":{"line":10,"column":15},"generated":{"line":1,"column":129}},{"source":"app\\models\\TechnicalReport.js","name":"INTEGER","original":{"line":10,"column":25},"generated":{"line":1,"column":131}},{"source":"app\\models\\TechnicalReport.js","name":"Sequelize","original":{"line":11,"column":16},"generated":{"line":1,"column":139}},{"source":"app\\models\\TechnicalReport.js","name":"Sequelize","original":{"line":11,"column":16},"generated":{"line":1,"column":150}},{"source":"app\\models\\TechnicalReport.js","name":"STRING","original":{"line":11,"column":26},"generated":{"line":1,"column":152}},{"source":"app\\models\\TechnicalReport.js","name":"Sequelize","original":{"line":12,"column":16},"generated":{"line":1,"column":159}},{"source":"app\\models\\TechnicalReport.js","name":"Sequelize","original":{"line":12,"column":16},"generated":{"line":1,"column":170}},{"source":"app\\models\\TechnicalReport.js","name":"STRING","original":{"line":12,"column":26},"generated":{"line":1,"column":172}},{"source":"app\\models\\TechnicalReport.js","name":"Sequelize","original":{"line":13,"column":18},"generated":{"line":1,"column":179}},{"source":"app\\models\\TechnicalReport.js","name":"Sequelize","original":{"line":13,"column":18},"generated":{"line":1,"column":192}},{"source":"app\\models\\TechnicalReport.js","name":"STRING","original":{"line":13,"column":28},"generated":{"line":1,"column":194}},{"source":"app\\models\\TechnicalReport.js","name":"Sequelize","original":{"line":14,"column":15},"generated":{"line":1,"column":201}},{"source":"app\\models\\TechnicalReport.js","name":"Sequelize","original":{"line":14,"column":15},"generated":{"line":1,"column":211}},{"source":"app\\models\\TechnicalReport.js","name":"INTEGER","original":{"line":14,"column":25},"generated":{"line":1,"column":213}},{"source":"app\\models\\TechnicalReport.js","original":{"line":16,"column":2},"generated":{"line":1,"column":222}},{"source":"app\\models\\TechnicalReport.js","original":{"line":17,"column":15},"generated":{"line":1,"column":223}},{"source":"app\\models\\TechnicalReport.js","original":{"line":17,"column":15},"generated":{"line":1,"column":233}},{"source":"app\\models\\TechnicalReport.js","original":{"line":18,"column":15},"generated":{"line":1,"column":248}},{"source":"app\\models\\TechnicalReport.js","original":{"line":18,"column":15},"generated":{"line":1,"column":259}},{"source":"app\\models\\TechnicalReport.js","original":{"line":19,"column":15},"generated":{"line":1,"column":261}},{"source":"app\\models\\TechnicalReport.js","original":{"line":19,"column":15},"generated":{"line":1,"column":272}},{"source":"app\\models\\TechnicalReport.js","name":"module","original":{"line":23,"column":0},"generated":{"line":1,"column":276}},{"source":"app\\models\\TechnicalReport.js","name":"exports","original":{"line":23,"column":7},"generated":{"line":1,"column":283}},{"source":"app\\models\\TechnicalReport.js","name":"TechnicalReport","original":{"line":23,"column":17},"generated":{"line":1,"column":291}}],"sources":{"app\\models\\TechnicalReport.js":"const Sequelize = require('sequelize')\r\nconst sequelize = require('./Base')\r\nconst TechnicalReport = sequelize.define(\r\n  'TechnicalReport',\r\n  {\r\n    Tech_SNO: {\r\n      type: Sequelize.INTEGER,\r\n      primaryKey: true\r\n    },\r\n    Tech_CODE: Sequelize.INTEGER,\r\n    Tech_DCODE: Sequelize.STRING,\r\n    Tech_Title: Sequelize.STRING,\r\n    Tech_Authors: Sequelize.STRING,\r\n    Tech_Year: Sequelize.INTEGER\r\n  },\r\n  {\r\n    tableName: 'Tech_reports',\r\n    updatedAt: false,\r\n    createdAt: false\r\n  }\r\n)\r\n\r\nmodule.exports = TechnicalReport\r\n"},"lineCount":null}},"hash":"22a758b9e42a6167c7bf69d8ba98fc57","cacheData":{"env":{}}}